{
  "version": "v0.4.0",
  "wardrobe_items": [
    {
      "id": "item_58bb2b31",
      "name": "Costume",
      "size": null,
      "status": "Available",
      "category": "Miscellaneous",
      "price": null,
      "location": "None",
      "condition": "Unknown",
      "notes": "None"
    },
    {
      "id": "item_79725b55",
      "name": "Weekly",
      "size": null,
      "status": "Available",
      "category": "Miscellaneous",
      "price": null,
      "location": "None",
      "condition": "Unknown",
      "notes": "None"
    },
    {
      "id": "item_0e7dcccb",
      "name": "Replacement",
      "size": null,
      "status": "Available",
      "category": "Miscellaneous",
      "price": null,
      "location": "None",
      "condition": "Unknown",
      "notes": "None"
    },
    {
      "id": "item_feb898ce",
      "name": "Charlie",
      "size": null,
      "status": "Available",
      "category": "Miscellaneous",
      "price": null,
      "location": "None",
      "condition": "Unknown",
      "notes": "None"
    },
    {
      "id": "item_464e3e51",
      "name": "Height",
      "size": null,
      "status": "Available",
      "category": "Miscellaneous",
      "price": null,
      "location": "None",
      "condition": "Unknown",
      "notes": "None"
    },
    {
      "id": "item_f6ddde26",
      "name": "Weight",
      "size": null,
      "status": "Available",
      "category": "Miscellaneous",
      "price": null,
      "location": "None",
      "condition": "Unknown",
      "notes": "None"
    },
    {
      "id": "item_6226d7fa",
      "name": "Head",
      "size": null,
      "status": "Available",
      "category": "Miscellaneous",
      "price": null,
      "location": "None",
      "condition": "Unknown",
      "notes": "None"
    },
    {
      "id": "item_00096626",
      "name": "Chest",
      "size": null,
      "status": "Available",
      "category": "Miscellaneous",
      "price": null,
      "location": "None",
      "condition": "Unknown",
      "notes": "None"
    },
    {
      "id": "item_f1134711",
      "name": "Waist",
      "size": null,
      "status": "Available",
      "category": "Miscellaneous",
      "price": null,
      "location": "None",
      "condition": "Unknown",
      "notes": "None"
    },
    {
      "id": "item_dfe95729",
      "name": "Hip",
      "size": null,
      "status": "Available",
      "category": "Miscellaneous",
      "price": null,
      "location": "None",
      "condition": "Unknown",
      "notes": "None"
    },
    {
      "id": "item_934115f1",
      "name": "Red",
      "size": null,
      "status": "Available",
      "category": "Miscellaneous",
      "price": null,
      "location": "None",
      "condition": "Unknown",
      "notes": "None"
    },
    {
      "id": "item_a7aae712",
      "name": "20.00",
      "size": null,
      "status": "Available",
      "category": "Miscellaneous",
      "price": null,
      "location": "None",
      "condition": "Unknown",
      "notes": "None"
    },
    {
      "id": "item_e18b71ee",
      "name": "$",
      "size": null,
      "status": "Available",
      "category": "Miscellaneous",
      "price": null,
      "location": "None",
      "condition": "Unknown",
      "notes": "None"
    },
    {
      "id": "item_29ed0349",
      "name": "150.00",
      "size": null,
      "status": "Available",
      "category": "Miscellaneous",
      "price": null,
      "location": "None",
      "condition": "Unknown",
      "notes": "None"
    },
    {
      "id": "item_2f940050",
      "name": "$",
      "size": null,
      "status": "Available",
      "category": "Miscellaneous",
      "price": null,
      "location": "None",
      "condition": "Unknown",
      "notes": "None"
    },
    {
      "id": "item_22361e09",
      "name": "5'1\"",
      "size": null,
      "status": "Available",
      "category": "Miscellaneous",
      "price": null,
      "location": "None",
      "condition": "Unknown",
      "notes": "None"
    },
    {
      "id": "item_6071a84c",
      "name": "110",
      "size": null,
      "status": "Available",
      "category": "Miscellaneous",
      "price": null,
      "location": "None",
      "condition": "Unknown",
      "notes": "None"
    },
    {
      "id": "item_c7beff99",
      "name": "21",
      "size": null,
      "status": "Available",
      "category": "Miscellaneous",
      "price": null,
      "location": "None",
      "condition": "Unknown",
      "notes": "None"
    },
    {
      "id": "item_2d66d608",
      "name": "35",
      "size": null,
      "status": "Available",
      "category": "Miscellaneous",
      "price": null,
      "location": "None",
      "condition": "Unknown",
      "notes": "None"
    },
    {
      "id": "item_b4a88ef2",
      "name": "31",
      "size": null,
      "status": "Available",
      "category": "Miscellaneous",
      "price": null,
      "location": "None",
      "condition": "Unknown",
      "notes": "None"
    },
    {
      "id": "item_279bf89d",
      "name": "36",
      "size": null,
      "status": "Available",
      "category": "Miscellaneous",
      "price": null,
      "location": "None",
      "condition": "Unknown",
      "notes": "None"
    },
    {
      "id": "item_f98cdb9e",
      "name": "Yellow",
      "size": null,
      "status": "Available",
      "category": "Miscellaneous",
      "price": null,
      "location": "None",
      "condition": "Unknown",
      "notes": "None"
    },
    {
      "id": "item_11f77e95",
      "name": "10.00",
      "size": null,
      "status": "Available",
      "category": "Miscellaneous",
      "price": null,
      "location": "None",
      "condition": "Unknown",
      "notes": "None"
    },
    {
      "id": "item_811dae6c",
      "name": "$",
      "size": null,
      "status": "Available",
      "category": "Miscellaneous",
      "price": null,
      "location": "None",
      "condition": "Unknown",
      "notes": "None"
    },
    {
      "id": "item_43ac11b0",
      "name": "100.00",
      "size": null,
      "status": "Available",
      "category": "Miscellaneous",
      "price": null,
      "location": "None",
      "condition": "Unknown",
      "notes": "None"
    },
    {
      "id": "item_d1c22f2a",
      "name": "$",
      "size": null,
      "status": "Available",
      "category": "Miscellaneous",
      "price": null,
      "location": "None",
      "condition": "Unknown",
      "notes": "None"
    },
    {
      "id": "item_760f191a",
      "name": "5'3\"",
      "size": null,
      "status": "Available",
      "category": "Miscellaneous",
      "price": null,
      "location": "None",
      "condition": "Unknown",
      "notes": "None"
    },
    {
      "id": "item_cc85985a",
      "name": "95",
      "size": null,
      "status": "Available",
      "category": "Miscellaneous",
      "price": null,
      "location": "None",
      "condition": "Unknown",
      "notes": "None"
    },
    {
      "id": "item_54b031ac",
      "name": "21",
      "size": null,
      "status": "Available",
      "category": "Miscellaneous",
      "price": null,
      "location": "None",
      "condition": "Unknown",
      "notes": "None"
    },
    {
      "id": "item_de203175",
      "name": "31",
      "size": null,
      "status": "Available",
      "category": "Miscellaneous",
      "price": null,
      "location": "None",
      "condition": "Unknown",
      "notes": "None"
    },
    {
      "id": "item_185e47f9",
      "name": "27",
      "size": null,
      "status": "Available",
      "category": "Miscellaneous",
      "price": null,
      "location": "None",
      "condition": "Unknown",
      "notes": "None"
    },
    {
      "id": "item_ef0a131c",
      "name": "32",
      "size": null,
      "status": "Available",
      "category": "Miscellaneous",
      "price": null,
      "location": "None",
      "condition": "Unknown",
      "notes": "None"
    },
    {
      "id": "item_322e775a",
      "name": "Sally",
      "size": null,
      "status": "Available",
      "category": "Miscellaneous",
      "price": null,
      "location": "None",
      "condition": "Unknown",
      "notes": "None"
    },
    {
      "id": "item_f238e5a1",
      "name": "Height",
      "size": null,
      "status": "Available",
      "category": "Miscellaneous",
      "price": null,
      "location": "None",
      "condition": "Unknown",
      "notes": "None"
    },
    {
      "id": "item_35d71a07",
      "name": "Weight",
      "size": null,
      "status": "Available",
      "category": "Miscellaneous",
      "price": null,
      "location": "None",
      "condition": "Unknown",
      "notes": "None"
    },
    {
      "id": "item_2d59eca8",
      "name": "Head",
      "size": null,
      "status": "Available",
      "category": "Miscellaneous",
      "price": null,
      "location": "None",
      "condition": "Unknown",
      "notes": "None"
    },
    {
      "id": "item_aebbd3c7",
      "name": "Chest",
      "size": null,
      "status": "Available",
      "category": "Miscellaneous",
      "price": null,
      "location": "None",
      "condition": "Unknown",
      "notes": "None"
    },
    {
      "id": "item_619c20f1",
      "name": "Waist",
      "size": null,
      "status": "Available",
      "category": "Miscellaneous",
      "price": null,
      "location": "None",
      "condition": "Unknown",
      "notes": "None"
    },
    {
      "id": "item_c5626644",
      "name": "Hip",
      "size": null,
      "status": "Available",
      "category": "Miscellaneous",
      "price": null,
      "location": "None",
      "condition": "Unknown",
      "notes": "None"
    },
    {
      "id": "item_d665b393",
      "name": "Pink",
      "size": null,
      "status": "Available",
      "category": "Miscellaneous",
      "price": null,
      "location": "None",
      "condition": "Unknown",
      "notes": "None"
    },
    {
      "id": "item_2e59c330",
      "name": "15.00",
      "size": null,
      "status": "Available",
      "category": "Miscellaneous",
      "price": null,
      "location": "None",
      "condition": "Unknown",
      "notes": "None"
    },
    {
      "id": "item_12ff6366",
      "name": "$",
      "size": null,
      "status": "Available",
      "category": "Miscellaneous",
      "price": null,
      "location": "None",
      "condition": "Unknown",
      "notes": "None"
    },
    {
      "id": "item_b21934ed",
      "name": "150.00",
      "size": null,
      "status": "Available",
      "category": "Miscellaneous",
      "price": null,
      "location": "None",
      "condition": "Unknown",
      "notes": "None"
    },
    {
      "id": "item_b1410e17",
      "name": "$",
      "size": null,
      "status": "Available",
      "category": "Miscellaneous",
      "price": null,
      "location": "None",
      "condition": "Unknown",
      "notes": "None"
    },
    {
      "id": "item_13dbe2ac",
      "name": "4'",
      "size": null,
      "status": "Available",
      "category": "Miscellaneous",
      "price": null,
      "location": "None",
      "condition": "Unknown",
      "notes": "None"
    },
    {
      "id": "item_bebac8f1",
      "name": "78",
      "size": null,
      "status": "Available",
      "category": "Miscellaneous",
      "price": null,
      "location": "None",
      "condition": "Unknown",
      "notes": "None"
    },
    {
      "id": "item_fbf3b090",
      "name": "21",
      "size": null,
      "status": "Available",
      "category": "Miscellaneous",
      "price": null,
      "location": "None",
      "condition": "Unknown",
      "notes": "None"
    },
    {
      "id": "item_dd7ff6b9",
      "name": "31",
      "size": null,
      "status": "Available",
      "category": "Miscellaneous",
      "price": null,
      "location": "None",
      "condition": "Unknown",
      "notes": "None"
    },
    {
      "id": "item_28d403a2",
      "name": "24",
      "size": null,
      "status": "Available",
      "category": "Miscellaneous",
      "price": null,
      "location": "None",
      "condition": "Unknown",
      "notes": "None"
    },
    {
      "id": "item_acd79cb9",
      "name": "30",
      "size": null,
      "status": "Available",
      "category": "Miscellaneous",
      "price": null,
      "location": "None",
      "condition": "Unknown",
      "notes": "None"
    },
    {
      "id": "item_8c9264c5",
      "name": "Yellow",
      "size": null,
      "status": "Available",
      "category": "Miscellaneous",
      "price": null,
      "location": "None",
      "condition": "Unknown",
      "notes": "None"
    },
    {
      "id": "item_049a10b5",
      "name": "20.00",
      "size": null,
      "status": "Available",
      "category": "Miscellaneous",
      "price": null,
      "location": "None",
      "condition": "Unknown",
      "notes": "None"
    },
    {
      "id": "item_489c6000",
      "name": "$",
      "size": null,
      "status": "Available",
      "category": "Miscellaneous",
      "price": null,
      "location": "None",
      "condition": "Unknown",
      "notes": "None"
    },
    {
      "id": "item_3ac6d837",
      "name": "200.00",
      "size": null,
      "status": "Available",
      "category": "Miscellaneous",
      "price": null,
      "location": "None",
      "condition": "Unknown",
      "notes": "None"
    },
    {
      "id": "item_f10f74a5",
      "name": "$",
      "size": null,
      "status": "Available",
      "category": "Miscellaneous",
      "price": null,
      "location": "None",
      "condition": "Unknown",
      "notes": "None"
    },
    {
      "id": "item_d3ceca39",
      "name": "4'",
      "size": null,
      "status": "Available",
      "category": "Miscellaneous",
      "price": null,
      "location": "None",
      "condition": "Unknown",
      "notes": "None"
    },
    {
      "id": "item_90c92267",
      "name": "83",
      "size": null,
      "status": "Available",
      "category": "Miscellaneous",
      "price": null,
      "location": "None",
      "condition": "Unknown",
      "notes": "None"
    },
    {
      "id": "item_9425cf80",
      "name": "20",
      "size": null,
      "status": "Available",
      "category": "Miscellaneous",
      "price": null,
      "location": "None",
      "condition": "Unknown",
      "notes": "None"
    },
    {
      "id": "item_1477219e",
      "name": "29",
      "size": null,
      "status": "Available",
      "category": "Miscellaneous",
      "price": null,
      "location": "None",
      "condition": "Unknown",
      "notes": "None"
    },
    {
      "id": "item_a4d03167",
      "name": "25",
      "size": null,
      "status": "Available",
      "category": "Miscellaneous",
      "price": null,
      "location": "None",
      "condition": "Unknown",
      "notes": "None"
    },
    {
      "id": "item_d1f9eefe",
      "name": "31",
      "size": null,
      "status": "Available",
      "category": "Miscellaneous",
      "price": null,
      "location": "None",
      "condition": "Unknown",
      "notes": "None"
    },
    {
      "id": "item_3159e984",
      "name": "Lucy",
      "size": null,
      "status": "Available",
      "category": "Miscellaneous",
      "price": null,
      "location": "None",
      "condition": "Unknown",
      "notes": "None"
    },
    {
      "id": "item_72b5a07a",
      "name": "Height",
      "size": null,
      "status": "Available",
      "category": "Miscellaneous",
      "price": null,
      "location": "None",
      "condition": "Unknown",
      "notes": "None"
    },
    {
      "id": "item_38842012",
      "name": "Weight",
      "size": null,
      "status": "Available",
      "category": "Miscellaneous",
      "price": null,
      "location": "None",
      "condition": "Unknown",
      "notes": "None"
    },
    {
      "id": "item_276228d6",
      "name": "Head",
      "size": null,
      "status": "Available",
      "category": "Miscellaneous",
      "price": null,
      "location": "None",
      "condition": "Unknown",
      "notes": "None"
    },
    {
      "id": "item_c664a9fa",
      "name": "Chest",
      "size": null,
      "status": "Available",
      "category": "Miscellaneous",
      "price": null,
      "location": "None",
      "condition": "Unknown",
      "notes": "None"
    },
    {
      "id": "item_81dd7407",
      "name": "Waist",
      "size": null,
      "status": "Available",
      "category": "Miscellaneous",
      "price": null,
      "location": "None",
      "condition": "Unknown",
      "notes": "None"
    },
    {
      "id": "item_466b273f",
      "name": "Hip",
      "size": null,
      "status": "Available",
      "category": "Miscellaneous",
      "price": null,
      "location": "None",
      "condition": "Unknown",
      "notes": "None"
    },
    {
      "id": "item_456c76ad",
      "name": "Blue",
      "size": null,
      "status": "Available",
      "category": "Miscellaneous",
      "price": null,
      "location": "None",
      "condition": "Unknown",
      "notes": "None"
    },
    {
      "id": "item_d4b82e3c",
      "name": "$",
      "size": null,
      "status": "Available",
      "category": "Miscellaneous",
      "price": null,
      "location": "None",
      "condition": "Unknown",
      "notes": "None"
    },
    {
      "id": "item_92c188c0",
      "name": "150.00",
      "size": null,
      "status": "Available",
      "category": "Miscellaneous",
      "price": null,
      "location": "None",
      "condition": "Unknown",
      "notes": "None"
    },
    {
      "id": "item_3791e9a0",
      "name": "$",
      "size": null,
      "status": "Available",
      "category": "Miscellaneous",
      "price": null,
      "location": "None",
      "condition": "Unknown",
      "notes": "None"
    },
    {
      "id": "item_d596d034",
      "name": "5'",
      "size": null,
      "status": "Available",
      "category": "Miscellaneous",
      "price": null,
      "location": "None",
      "condition": "Unknown",
      "notes": "None"
    },
    {
      "id": "item_83fa9b40",
      "name": "105",
      "size": null,
      "status": "Available",
      "category": "Miscellaneous",
      "price": null,
      "location": "None",
      "condition": "Unknown",
      "notes": "None"
    },
    {
      "id": "item_a1591bf9",
      "name": "22",
      "size": null,
      "status": "Available",
      "category": "Miscellaneous",
      "price": null,
      "location": "None",
      "condition": "Unknown",
      "notes": "None"
    },
    {
      "id": "item_0719c7cd",
      "name": "36",
      "size": null,
      "status": "Available",
      "category": "Miscellaneous",
      "price": null,
      "location": "None",
      "condition": "Unknown",
      "notes": "None"
    },
    {
      "id": "item_605389d0",
      "name": "28",
      "size": null,
      "status": "Available",
      "category": "Miscellaneous",
      "price": null,
      "location": "None",
      "condition": "Unknown",
      "notes": "None"
    },
    {
      "id": "item_f84f7509",
      "name": "37",
      "size": null,
      "status": "Available",
      "category": "Miscellaneous",
      "price": null,
      "location": "None",
      "condition": "Unknown",
      "notes": "None"
    },
    {
      "id": "item_774ea250",
      "name": "Yellow",
      "size": null,
      "status": "Available",
      "category": "Miscellaneous",
      "price": null,
      "location": "None",
      "condition": "Unknown",
      "notes": "None"
    },
    {
      "id": "item_32da708a",
      "name": "$",
      "size": null,
      "status": "Available",
      "category": "Miscellaneous",
      "price": null,
      "location": "None",
      "condition": "Unknown",
      "notes": "None"
    },
    {
      "id": "item_0157b42c",
      "name": "250.00",
      "size": null,
      "status": "Available",
      "category": "Miscellaneous",
      "price": null,
      "location": "None",
      "condition": "Unknown",
      "notes": "None"
    },
    {
      "id": "item_10a3be75",
      "name": "$",
      "size": null,
      "status": "Available",
      "category": "Miscellaneous",
      "price": null,
      "location": "None",
      "condition": "Unknown",
      "notes": "None"
    },
    {
      "id": "item_89e65159",
      "name": "5'",
      "size": null,
      "status": "Available",
      "category": "Miscellaneous",
      "price": null,
      "location": "None",
      "condition": "Unknown",
      "notes": "None"
    },
    {
      "id": "item_c60eef4e",
      "name": "95",
      "size": null,
      "status": "Available",
      "category": "Miscellaneous",
      "price": null,
      "location": "None",
      "condition": "Unknown",
      "notes": "None"
    },
    {
      "id": "item_0a9b9cab",
      "name": "21",
      "size": null,
      "status": "Available",
      "category": "Miscellaneous",
      "price": null,
      "location": "None",
      "condition": "Unknown",
      "notes": "None"
    },
    {
      "id": "item_7e40f63c",
      "name": "31",
      "size": null,
      "status": "Available",
      "category": "Miscellaneous",
      "price": null,
      "location": "None",
      "condition": "Unknown",
      "notes": "None"
    },
    {
      "id": "item_e01844d3",
      "name": "27",
      "size": null,
      "status": "Available",
      "category": "Miscellaneous",
      "price": null,
      "location": "None",
      "condition": "Unknown",
      "notes": "None"
    },
    {
      "id": "item_0b4b6fd7",
      "name": "33",
      "size": null,
      "status": "Available",
      "category": "Miscellaneous",
      "price": null,
      "location": "None",
      "condition": "Unknown",
      "notes": "None"
    },
    {
      "id": "item_50fc15cd",
      "name": "Linus",
      "size": null,
      "status": "Available",
      "category": "Miscellaneous",
      "price": null,
      "location": "None",
      "condition": "Unknown",
      "notes": "None"
    },
    {
      "id": "item_467a6061",
      "name": "Height",
      "size": null,
      "status": "Available",
      "category": "Miscellaneous",
      "price": null,
      "location": "None",
      "condition": "Unknown",
      "notes": "None"
    },
    {
      "id": "item_0ac9cd3b",
      "name": "Weight",
      "size": null,
      "status": "Available",
      "category": "Miscellaneous",
      "price": null,
      "location": "None",
      "condition": "Unknown",
      "notes": "None"
    },
    {
      "id": "item_b5edbac7",
      "name": "Head",
      "size": null,
      "status": "Available",
      "category": "Miscellaneous",
      "price": null,
      "location": "None",
      "condition": "Unknown",
      "notes": "None"
    },
    {
      "id": "item_4491547f",
      "name": "Chest",
      "size": null,
      "status": "Available",
      "category": "Miscellaneous",
      "price": null,
      "location": "None",
      "condition": "Unknown",
      "notes": "None"
    },
    {
      "id": "item_a1878733",
      "name": "Waist",
      "size": null,
      "status": "Available",
      "category": "Miscellaneous",
      "price": null,
      "location": "None",
      "condition": "Unknown",
      "notes": "None"
    },
    {
      "id": "item_1208d5b5",
      "name": "Hip",
      "size": null,
      "status": "Available",
      "category": "Miscellaneous",
      "price": null,
      "location": "None",
      "condition": "Unknown",
      "notes": "None"
    },
    {
      "id": "item_7e7e0b4a",
      "name": "Orange",
      "size": null,
      "status": "Available",
      "category": "Miscellaneous",
      "price": null,
      "location": "None",
      "condition": "Unknown",
      "notes": "None"
    },
    {
      "id": "item_78930e95",
      "name": "20.00",
      "size": null,
      "status": "Available",
      "category": "Miscellaneous",
      "price": null,
      "location": "None",
      "condition": "Unknown",
      "notes": "None"
    },
    {
      "id": "item_0ce85ca9",
      "name": "$",
      "size": null,
      "status": "Available",
      "category": "Miscellaneous",
      "price": null,
      "location": "None",
      "condition": "Unknown",
      "notes": "None"
    },
    {
      "id": "item_e2287923",
      "name": "175.00",
      "size": null,
      "status": "Available",
      "category": "Miscellaneous",
      "price": null,
      "location": "None",
      "condition": "Unknown",
      "notes": "None"
    },
    {
      "id": "item_210824a4",
      "name": "$",
      "size": null,
      "status": "Available",
      "category": "Miscellaneous",
      "price": null,
      "location": "None",
      "condition": "Unknown",
      "notes": "None"
    },
    {
      "id": "item_41b57dca",
      "name": "5'2\"",
      "size": null,
      "status": "Available",
      "category": "Miscellaneous",
      "price": null,
      "location": "None",
      "condition": "Unknown",
      "notes": "None"
    },
    {
      "id": "item_eb418c88",
      "name": "110",
      "size": null,
      "status": "Available",
      "category": "Miscellaneous",
      "price": null,
      "location": "None",
      "condition": "Unknown",
      "notes": "None"
    },
    {
      "id": "item_49e6e65e",
      "name": "22",
      "size": null,
      "status": "Available",
      "category": "Miscellaneous",
      "price": null,
      "location": "None",
      "condition": "Unknown",
      "notes": "None"
    },
    {
      "id": "item_4b21e712",
      "name": "32",
      "size": null,
      "status": "Available",
      "category": "Miscellaneous",
      "price": null,
      "location": "None",
      "condition": "Unknown",
      "notes": "None"
    },
    {
      "id": "item_403d3bb9",
      "name": "29",
      "size": null,
      "status": "Available",
      "category": "Miscellaneous",
      "price": null,
      "location": "None",
      "condition": "Unknown",
      "notes": "None"
    },
    {
      "id": "item_e8ccb16e",
      "name": "34",
      "size": null,
      "status": "Available",
      "category": "Miscellaneous",
      "price": null,
      "location": "None",
      "condition": "Unknown",
      "notes": "None"
    },
    {
      "id": "item_3f22b55b",
      "name": "Violet",
      "size": null,
      "status": "Available",
      "category": "Miscellaneous",
      "price": null,
      "location": "None",
      "condition": "Unknown",
      "notes": "None"
    },
    {
      "id": "item_37dbafee",
      "name": "Height",
      "size": null,
      "status": "Available",
      "category": "Miscellaneous",
      "price": null,
      "location": "None",
      "condition": "Unknown",
      "notes": "None"
    },
    {
      "id": "item_cda96475",
      "name": "Weight",
      "size": null,
      "status": "Available",
      "category": "Miscellaneous",
      "price": null,
      "location": "None",
      "condition": "Unknown",
      "notes": "None"
    },
    {
      "id": "item_8a4c4ab3",
      "name": "Head",
      "size": null,
      "status": "Available",
      "category": "Miscellaneous",
      "price": null,
      "location": "None",
      "condition": "Unknown",
      "notes": "None"
    },
    {
      "id": "item_ae446004",
      "name": "Chest",
      "size": null,
      "status": "Available",
      "category": "Miscellaneous",
      "price": null,
      "location": "None",
      "condition": "Unknown",
      "notes": "None"
    },
    {
      "id": "item_300a0e97",
      "name": "Waist",
      "size": null,
      "status": "Available",
      "category": "Miscellaneous",
      "price": null,
      "location": "None",
      "condition": "Unknown",
      "notes": "None"
    },
    {
      "id": "item_18f71caf",
      "name": "Hip",
      "size": null,
      "status": "Available",
      "category": "Miscellaneous",
      "price": null,
      "location": "None",
      "condition": "Unknown",
      "notes": "None"
    },
    {
      "id": "item_0afda129",
      "name": "Purple",
      "size": null,
      "status": "Available",
      "category": "Miscellaneous",
      "price": null,
      "location": "None",
      "condition": "Unknown",
      "notes": "None"
    },
    {
      "id": "item_dbdb9ced",
      "name": "20.00",
      "size": null,
      "status": "Available",
      "category": "Miscellaneous",
      "price": null,
      "location": "None",
      "condition": "Unknown",
      "notes": "None"
    },
    {
      "id": "item_769f2b45",
      "name": "$",
      "size": null,
      "status": "Available",
      "category": "Miscellaneous",
      "price": null,
      "location": "None",
      "condition": "Unknown",
      "notes": "None"
    },
    {
      "id": "item_1e55629d",
      "name": "250.00",
      "size": null,
      "status": "Available",
      "category": "Miscellaneous",
      "price": null,
      "location": "None",
      "condition": "Unknown",
      "notes": "None"
    },
    {
      "id": "item_30cdc495",
      "name": "$",
      "size": null,
      "status": "Available",
      "category": "Miscellaneous",
      "price": null,
      "location": "None",
      "condition": "Unknown",
      "notes": "None"
    },
    {
      "id": "item_06f9b48d",
      "name": "5'",
      "size": null,
      "status": "Available",
      "category": "Miscellaneous",
      "price": null,
      "location": "None",
      "condition": "Unknown",
      "notes": "None"
    },
    {
      "id": "item_4b6df0b5",
      "name": "90",
      "size": null,
      "status": "Available",
      "category": "Miscellaneous",
      "price": null,
      "location": "None",
      "condition": "Unknown",
      "notes": "None"
    },
    {
      "id": "item_5452967c",
      "name": "21",
      "size": null,
      "status": "Available",
      "category": "Miscellaneous",
      "price": null,
      "location": "None",
      "condition": "Unknown",
      "notes": "None"
    },
    {
      "id": "item_c45bac79",
      "name": "30",
      "size": null,
      "status": "Available",
      "category": "Miscellaneous",
      "price": null,
      "location": "None",
      "condition": "Unknown",
      "notes": "None"
    },
    {
      "id": "item_1717f86d",
      "name": "26",
      "size": null,
      "status": "Available",
      "category": "Miscellaneous",
      "price": null,
      "location": "None",
      "condition": "Unknown",
      "notes": "None"
    },
    {
      "id": "item_36974852",
      "name": "33",
      "size": null,
      "status": "Available",
      "category": "Miscellaneous",
      "price": null,
      "location": "None",
      "condition": "Unknown",
      "notes": "None"
    },
    {
      "id": "item_a213805f",
      "name": "Snoopy",
      "size": null,
      "status": "Available",
      "category": "Miscellaneous",
      "price": null,
      "location": "None",
      "condition": "Unknown",
      "notes": "None"
    },
    {
      "id": "item_e3699b4f",
      "name": "Height",
      "size": null,
      "status": "Available",
      "category": "Miscellaneous",
      "price": null,
      "location": "None",
      "condition": "Unknown",
      "notes": "None"
    },
    {
      "id": "item_c5765831",
      "name": "Weight",
      "size": null,
      "status": "Available",
      "category": "Miscellaneous",
      "price": null,
      "location": "None",
      "condition": "Unknown",
      "notes": "None"
    },
    {
      "id": "item_6047de5b",
      "name": "Head",
      "size": null,
      "status": "Available",
      "category": "Miscellaneous",
      "price": null,
      "location": "None",
      "condition": "Unknown",
      "notes": "None"
    },
    {
      "id": "item_1065ae70",
      "name": "Chest",
      "size": null,
      "status": "Available",
      "category": "Miscellaneous",
      "price": null,
      "location": "None",
      "condition": "Unknown",
      "notes": "None"
    },
    {
      "id": "item_bd90358b",
      "name": "Waist",
      "size": null,
      "status": "Available",
      "category": "Miscellaneous",
      "price": null,
      "location": "None",
      "condition": "Unknown",
      "notes": "None"
    },
    {
      "id": "item_b071e7e6",
      "name": "Hip",
      "size": null,
      "status": "Available",
      "category": "Miscellaneous",
      "price": null,
      "location": "None",
      "condition": "Unknown",
      "notes": "None"
    },
    {
      "id": "item_06a8f3ce",
      "name": "White",
      "size": null,
      "status": "Available",
      "category": "Miscellaneous",
      "price": null,
      "location": "None",
      "condition": "Unknown",
      "notes": "None"
    },
    {
      "id": "item_04995af4",
      "name": "$",
      "size": null,
      "status": "Available",
      "category": "Miscellaneous",
      "price": null,
      "location": "None",
      "condition": "Unknown",
      "notes": "None"
    },
    {
      "id": "item_e0d4a44d",
      "name": "150.00",
      "size": null,
      "status": "Available",
      "category": "Miscellaneous",
      "price": null,
      "location": "None",
      "condition": "Unknown",
      "notes": "None"
    },
    {
      "id": "item_b1cb6172",
      "name": "$",
      "size": null,
      "status": "Available",
      "category": "Miscellaneous",
      "price": null,
      "location": "None",
      "condition": "Unknown",
      "notes": "None"
    },
    {
      "id": "item_e77269ec",
      "name": "6'2\"",
      "size": null,
      "status": "Available",
      "category": "Miscellaneous",
      "price": null,
      "location": "None",
      "condition": "Unknown",
      "notes": "None"
    },
    {
      "id": "item_f129d1c5",
      "name": "195",
      "size": null,
      "status": "Available",
      "category": "Miscellaneous",
      "price": null,
      "location": "None",
      "condition": "Unknown",
      "notes": "None"
    },
    {
      "id": "item_cceee87e",
      "name": "22",
      "size": null,
      "status": "Available",
      "category": "Miscellaneous",
      "price": null,
      "location": "None",
      "condition": "Unknown",
      "notes": "None"
    },
    {
      "id": "item_bf1ccda4",
      "name": "43",
      "size": null,
      "status": "Available",
      "category": "Miscellaneous",
      "price": null,
      "location": "None",
      "condition": "Unknown",
      "notes": "None"
    },
    {
      "id": "item_69e67e64",
      "name": "37",
      "size": null,
      "status": "Available",
      "category": "Miscellaneous",
      "price": null,
      "location": "None",
      "condition": "Unknown",
      "notes": "None"
    },
    {
      "id": "item_ca458097",
      "name": "43",
      "size": null,
      "status": "Available",
      "category": "Miscellaneous",
      "price": null,
      "location": "None",
      "condition": "Unknown",
      "notes": "None"
    },
    {
      "id": "item_d1f7496f",
      "name": "White",
      "size": null,
      "status": "Available",
      "category": "Miscellaneous",
      "price": null,
      "location": "None",
      "condition": "Unknown",
      "notes": "None"
    },
    {
      "id": "item_08d3d35a",
      "name": "$",
      "size": null,
      "status": "Available",
      "category": "Miscellaneous",
      "price": null,
      "location": "None",
      "condition": "Unknown",
      "notes": "None"
    },
    {
      "id": "item_0167fbec",
      "name": "50.00",
      "size": null,
      "status": "Available",
      "category": "Miscellaneous",
      "price": null,
      "location": "None",
      "condition": "Unknown",
      "notes": "None"
    },
    {
      "id": "item_e37cd7e6",
      "name": "$",
      "size": null,
      "status": "Available",
      "category": "Miscellaneous",
      "price": null,
      "location": "None",
      "condition": "Unknown",
      "notes": "None"
    },
    {
      "id": "item_0dbb9d2d",
      "name": "White",
      "size": null,
      "status": "Available",
      "category": "Miscellaneous",
      "price": null,
      "location": "None",
      "condition": "Unknown",
      "notes": "None"
    },
    {
      "id": "item_4e1190ba",
      "name": "$",
      "size": null,
      "status": "Available",
      "category": "Miscellaneous",
      "price": null,
      "location": "None",
      "condition": "Unknown",
      "notes": "None"
    },
    {
      "id": "item_f74229ae",
      "name": "65.00",
      "size": null,
      "status": "Available",
      "category": "Miscellaneous",
      "price": null,
      "location": "None",
      "condition": "Unknown",
      "notes": "None"
    },
    {
      "id": "item_912a1902",
      "name": "$",
      "size": null,
      "status": "Available",
      "category": "Miscellaneous",
      "price": null,
      "location": "None",
      "condition": "Unknown",
      "notes": "None"
    },
    {
      "id": "item_b753f412",
      "name": "Red",
      "size": null,
      "status": "Available",
      "category": "Miscellaneous",
      "price": null,
      "location": "None",
      "condition": "Unknown",
      "notes": "None"
    },
    {
      "id": "item_0695ee77",
      "name": "5.00",
      "size": null,
      "status": "Available",
      "category": "Miscellaneous",
      "price": null,
      "location": "None",
      "condition": "Unknown",
      "notes": "None"
    },
    {
      "id": "item_4d823526",
      "name": "$",
      "size": null,
      "status": "Available",
      "category": "Miscellaneous",
      "price": null,
      "location": "None",
      "condition": "Unknown",
      "notes": "None"
    },
    {
      "id": "item_d4b63da6",
      "name": "25.00",
      "size": null,
      "status": "Available",
      "category": "Miscellaneous",
      "price": null,
      "location": "None",
      "condition": "Unknown",
      "notes": "None"
    },
    {
      "id": "item_ee45d6cd",
      "name": "$",
      "size": null,
      "status": "Available",
      "category": "Miscellaneous",
      "price": null,
      "location": "None",
      "condition": "Unknown",
      "notes": "None"
    },
    {
      "id": "item_cf431003",
      "name": "Red",
      "size": null,
      "status": "Available",
      "category": "Miscellaneous",
      "price": null,
      "location": "None",
      "condition": "Unknown",
      "notes": "None"
    },
    {
      "id": "item_8de1baf0",
      "name": "5.00",
      "size": null,
      "status": "Available",
      "category": "Miscellaneous",
      "price": null,
      "location": "None",
      "condition": "Unknown",
      "notes": "None"
    },
    {
      "id": "item_c53d1e10",
      "name": "$",
      "size": null,
      "status": "Available",
      "category": "Miscellaneous",
      "price": null,
      "location": "None",
      "condition": "Unknown",
      "notes": "None"
    },
    {
      "id": "item_ca3c9242",
      "name": "15.00",
      "size": null,
      "status": "Available",
      "category": "Miscellaneous",
      "price": null,
      "location": "None",
      "condition": "Unknown",
      "notes": "None"
    },
    {
      "id": "item_a1c49c85",
      "name": "$",
      "size": null,
      "status": "Available",
      "category": "Miscellaneous",
      "price": null,
      "location": "None",
      "condition": "Unknown",
      "notes": "None"
    },
    {
      "id": "item_0c12fa27",
      "name": "Distressed",
      "size": null,
      "status": "Available",
      "category": "Miscellaneous",
      "price": null,
      "location": "None",
      "condition": "Unknown",
      "notes": "None"
    },
    {
      "id": "item_97492ed9",
      "name": "5.00",
      "size": null,
      "status": "Available",
      "category": "Miscellaneous",
      "price": null,
      "location": "None",
      "condition": "Unknown",
      "notes": "None"
    },
    {
      "id": "item_33b827c6",
      "name": "$",
      "size": null,
      "status": "Available",
      "category": "Miscellaneous",
      "price": null,
      "location": "None",
      "condition": "Unknown",
      "notes": "None"
    },
    {
      "id": "item_78a498f7",
      "name": "15.00",
      "size": null,
      "status": "Available",
      "category": "Miscellaneous",
      "price": null,
      "location": "None",
      "condition": "Unknown",
      "notes": "None"
    },
    {
      "id": "item_c00aedc3",
      "name": "$",
      "size": null,
      "status": "Available",
      "category": "Miscellaneous",
      "price": null,
      "location": "None",
      "condition": "Unknown",
      "notes": "None"
    },
    {
      "id": "item_5ae7b665",
      "name": "Santa",
      "size": null,
      "status": "Available",
      "category": "Miscellaneous",
      "price": null,
      "location": "None",
      "condition": "Unknown",
      "notes": "None"
    },
    {
      "id": "item_d598e892",
      "name": "5.00",
      "size": null,
      "status": "Available",
      "category": "Miscellaneous",
      "price": null,
      "location": "None",
      "condition": "Unknown",
      "notes": "None"
    },
    {
      "id": "item_13c0320c",
      "name": "$",
      "size": null,
      "status": "Available",
      "category": "Miscellaneous",
      "price": null,
      "location": "None",
      "condition": "Unknown",
      "notes": "None"
    },
    {
      "id": "item_9baff605",
      "name": "35.00",
      "size": null,
      "status": "Available",
      "category": "Miscellaneous",
      "price": null,
      "location": "None",
      "condition": "Unknown",
      "notes": "None"
    },
    {
      "id": "item_d8c797b5",
      "name": "$",
      "size": null,
      "status": "Available",
      "category": "Miscellaneous",
      "price": null,
      "location": "None",
      "condition": "Unknown",
      "notes": "None"
    },
    {
      "id": "item_817cb13f",
      "name": "White",
      "size": null,
      "status": "Available",
      "category": "Miscellaneous",
      "price": null,
      "location": "None",
      "condition": "Unknown",
      "notes": "None"
    },
    {
      "id": "item_fb086956",
      "name": "5.00",
      "size": null,
      "status": "Available",
      "category": "Miscellaneous",
      "price": null,
      "location": "None",
      "condition": "Unknown",
      "notes": "None"
    },
    {
      "id": "item_012b19a8",
      "name": "$",
      "size": null,
      "status": "Available",
      "category": "Miscellaneous",
      "price": null,
      "location": "None",
      "condition": "Unknown",
      "notes": "None"
    },
    {
      "id": "item_d95c6aa1",
      "name": "50.00",
      "size": null,
      "status": "Available",
      "category": "Miscellaneous",
      "price": null,
      "location": "None",
      "condition": "Unknown",
      "notes": "None"
    },
    {
      "id": "item_ce9717f3",
      "name": "$",
      "size": null,
      "status": "Available",
      "category": "Miscellaneous",
      "price": null,
      "location": "None",
      "condition": "Unknown",
      "notes": "None"
    },
    {
      "id": "item_5d03b4cc",
      "name": "Aviator",
      "size": null,
      "status": "Available",
      "category": "Miscellaneous",
      "price": null,
      "location": "None",
      "condition": "Unknown",
      "notes": "None"
    },
    {
      "id": "item_27d73b9d",
      "name": "5.00",
      "size": null,
      "status": "Available",
      "category": "Miscellaneous",
      "price": null,
      "location": "None",
      "condition": "Unknown",
      "notes": "None"
    },
    {
      "id": "item_da910690",
      "name": "$",
      "size": null,
      "status": "Available",
      "category": "Miscellaneous",
      "price": null,
      "location": "None",
      "condition": "Unknown",
      "notes": "None"
    },
    {
      "id": "item_d2607951",
      "name": "50.00",
      "size": null,
      "status": "Available",
      "category": "Miscellaneous",
      "price": null,
      "location": "None",
      "condition": "Unknown",
      "notes": "None"
    },
    {
      "id": "item_e7fc7121",
      "name": "$",
      "size": null,
      "status": "Available",
      "category": "Miscellaneous",
      "price": null,
      "location": "None",
      "condition": "Unknown",
      "notes": "None"
    },
    {
      "id": "item_2f30154c",
      "name": "Patty",
      "size": null,
      "status": "Available",
      "category": "Miscellaneous",
      "price": null,
      "location": "None",
      "condition": "Unknown",
      "notes": "None"
    },
    {
      "id": "item_62dd84bd",
      "name": "Height",
      "size": null,
      "status": "Available",
      "category": "Miscellaneous",
      "price": null,
      "location": "None",
      "condition": "Unknown",
      "notes": "None"
    },
    {
      "id": "item_73a97226",
      "name": "Weight",
      "size": null,
      "status": "Available",
      "category": "Miscellaneous",
      "price": null,
      "location": "None",
      "condition": "Unknown",
      "notes": "None"
    },
    {
      "id": "item_6e513043",
      "name": "Head",
      "size": null,
      "status": "Available",
      "category": "Miscellaneous",
      "price": null,
      "location": "None",
      "condition": "Unknown",
      "notes": "None"
    },
    {
      "id": "item_6a8995b2",
      "name": "Chest",
      "size": null,
      "status": "Available",
      "category": "Miscellaneous",
      "price": null,
      "location": "None",
      "condition": "Unknown",
      "notes": "None"
    },
    {
      "id": "item_9abcb8ed",
      "name": "Waist",
      "size": null,
      "status": "Available",
      "category": "Miscellaneous",
      "price": null,
      "location": "None",
      "condition": "Unknown",
      "notes": "None"
    },
    {
      "id": "item_cf837f23",
      "name": "Hip",
      "size": null,
      "status": "Available",
      "category": "Miscellaneous",
      "price": null,
      "location": "None",
      "condition": "Unknown",
      "notes": "None"
    },
    {
      "id": "item_4283c7fc",
      "name": "Orange",
      "size": null,
      "status": "Available",
      "category": "Miscellaneous",
      "price": null,
      "location": "None",
      "condition": "Unknown",
      "notes": "None"
    },
    {
      "id": "item_4777d91d",
      "name": "15.00",
      "size": null,
      "status": "Available",
      "category": "Miscellaneous",
      "price": null,
      "location": "None",
      "condition": "Unknown",
      "notes": "None"
    },
    {
      "id": "item_1addc4da",
      "name": "$",
      "size": null,
      "status": "Available",
      "category": "Miscellaneous",
      "price": null,
      "location": "None",
      "condition": "Unknown",
      "notes": "None"
    },
    {
      "id": "item_2f5664b6",
      "name": "150.00",
      "size": null,
      "status": "Available",
      "category": "Miscellaneous",
      "price": null,
      "location": "None",
      "condition": "Unknown",
      "notes": "None"
    },
    {
      "id": "item_6a63a48d",
      "name": "$",
      "size": null,
      "status": "Available",
      "category": "Miscellaneous",
      "price": null,
      "location": "None",
      "condition": "Unknown",
      "notes": "None"
    },
    {
      "id": "item_32bd0792",
      "name": "5'2\"",
      "size": null,
      "status": "Available",
      "category": "Miscellaneous",
      "price": null,
      "location": "None",
      "condition": "Unknown",
      "notes": "None"
    },
    {
      "id": "item_e2638fde",
      "name": "110",
      "size": null,
      "status": "Available",
      "category": "Miscellaneous",
      "price": null,
      "location": "None",
      "condition": "Unknown",
      "notes": "None"
    },
    {
      "id": "item_26c26893",
      "name": "22",
      "size": null,
      "status": "Available",
      "category": "Miscellaneous",
      "price": null,
      "location": "None",
      "condition": "Unknown",
      "notes": "None"
    },
    {
      "id": "item_a94f7f98",
      "name": "32",
      "size": null,
      "status": "Available",
      "category": "Miscellaneous",
      "price": null,
      "location": "None",
      "condition": "Unknown",
      "notes": "None"
    },
    {
      "id": "item_158b11b6",
      "name": "29",
      "size": null,
      "status": "Available",
      "category": "Miscellaneous",
      "price": null,
      "location": "None",
      "condition": "Unknown",
      "notes": "None"
    },
    {
      "id": "item_9b441131",
      "name": "34",
      "size": null,
      "status": "Available",
      "category": "Miscellaneous",
      "price": null,
      "location": "None",
      "condition": "Unknown",
      "notes": "None"
    },
    {
      "id": "item_88931db3",
      "name": "Frieda",
      "size": null,
      "status": "Available",
      "category": "Miscellaneous",
      "price": null,
      "location": "None",
      "condition": "Unknown",
      "notes": "None"
    },
    {
      "id": "item_1b34fea1",
      "name": "Height",
      "size": null,
      "status": "Available",
      "category": "Miscellaneous",
      "price": null,
      "location": "None",
      "condition": "Unknown",
      "notes": "None"
    },
    {
      "id": "item_926df4f1",
      "name": "Weight",
      "size": null,
      "status": "Available",
      "category": "Miscellaneous",
      "price": null,
      "location": "None",
      "condition": "Unknown",
      "notes": "None"
    },
    {
      "id": "item_05ef795b",
      "name": "Head",
      "size": null,
      "status": "Available",
      "category": "Miscellaneous",
      "price": null,
      "location": "None",
      "condition": "Unknown",
      "notes": "None"
    },
    {
      "id": "item_ecb56447",
      "name": "Chest",
      "size": null,
      "status": "Available",
      "category": "Miscellaneous",
      "price": null,
      "location": "None",
      "condition": "Unknown",
      "notes": "None"
    },
    {
      "id": "item_decad6d3",
      "name": "Waist",
      "size": null,
      "status": "Available",
      "category": "Miscellaneous",
      "price": null,
      "location": "None",
      "condition": "Unknown",
      "notes": "None"
    },
    {
      "id": "item_d5a86933",
      "name": "Hip",
      "size": null,
      "status": "Available",
      "category": "Miscellaneous",
      "price": null,
      "location": "None",
      "condition": "Unknown",
      "notes": "None"
    },
    {
      "id": "item_119b112b",
      "name": "Yellow/White",
      "size": null,
      "status": "Available",
      "category": "Miscellaneous",
      "price": null,
      "location": "None",
      "condition": "Unknown",
      "notes": "None"
    },
    {
      "id": "item_d4582bdc",
      "name": "15.00",
      "size": null,
      "status": "Available",
      "category": "Miscellaneous",
      "price": null,
      "location": "None",
      "condition": "Unknown",
      "notes": "None"
    },
    {
      "id": "item_e733bcbc",
      "name": "$",
      "size": null,
      "status": "Available",
      "category": "Miscellaneous",
      "price": null,
      "location": "None",
      "condition": "Unknown",
      "notes": "None"
    },
    {
      "id": "item_7432390c",
      "name": "150.00",
      "size": null,
      "status": "Available",
      "category": "Miscellaneous",
      "price": null,
      "location": "None",
      "condition": "Unknown",
      "notes": "None"
    },
    {
      "id": "item_3a0ed601",
      "name": "$",
      "size": null,
      "status": "Available",
      "category": "Miscellaneous",
      "price": null,
      "location": "None",
      "condition": "Unknown",
      "notes": "None"
    },
    {
      "id": "item_4fd9f6a7",
      "name": "5'2\"",
      "size": null,
      "status": "Available",
      "category": "Miscellaneous",
      "price": null,
      "location": "None",
      "condition": "Unknown",
      "notes": "None"
    },
    {
      "id": "item_6612f3e5",
      "name": "110",
      "size": null,
      "status": "Available",
      "category": "Miscellaneous",
      "price": null,
      "location": "None",
      "condition": "Unknown",
      "notes": "None"
    },
    {
      "id": "item_79c0f04a",
      "name": "22",
      "size": null,
      "status": "Available",
      "category": "Miscellaneous",
      "price": null,
      "location": "None",
      "condition": "Unknown",
      "notes": "None"
    },
    {
      "id": "item_abb8f98d",
      "name": "32",
      "size": null,
      "status": "Available",
      "category": "Miscellaneous",
      "price": null,
      "location": "None",
      "condition": "Unknown",
      "notes": "None"
    },
    {
      "id": "item_584f2a15",
      "name": "29",
      "size": null,
      "status": "Available",
      "category": "Miscellaneous",
      "price": null,
      "location": "None",
      "condition": "Unknown",
      "notes": "None"
    },
    {
      "id": "item_9c16fef0",
      "name": "34",
      "size": null,
      "status": "Available",
      "category": "Miscellaneous",
      "price": null,
      "location": "None",
      "condition": "Unknown",
      "notes": "None"
    },
    {
      "id": "item_e8ef3010",
      "name": "Measurements",
      "size": null,
      "status": "Available",
      "category": "Miscellaneous",
      "price": null,
      "location": "None",
      "condition": "Unknown",
      "notes": "None"
    }
  ],
  "categories": [
    {
      "id": "miscellaneous",
      "name": "Miscellaneous",
      "description": "Inventory items in the Miscellaneous category"
    }
  ]
}